cf_secure_edge/__init__.py
cf_secure_edge/cf_token.py
cf_secure_edge-0.0.1.dist-info/METADATA
cf_secure_edge-0.0.1.dist-info/WHEEL
cf_secure_edge-0.0.1.dist-info/top_level.txt
cf_secure_edge-0.0.1.dist-info/RECORD
