Metadata-Version: 2.1
Name: cf-secure-edge
Version: 0.0.1
Summary: AWS CloudFront token generator
Author-email: ICS Compute <dev-ops.data@icscompute.com>
Project-URL: Homepage, https://github.com/ics-compute/cloudfront-token-generator-py 
Project-URL: Bug Tracker, https://github.com/ics-compute/cloudfront-token-generator-py /issues
Classifier: Programming Language :: Python :: 3
Classifier: License :: OSI Approved :: MIT License
Classifier: Operating System :: OS Independent
Requires-Python: >=3.7
Requires-Dist: pyjwt ==2.8.0
Requires-Dist: ksuid ==1.3
